LICENSE
MANIFEST.in
README.md
setup.py
django_thermostat/__init__.py
django_thermostat/admin.py
django_thermostat/auth.py
django_thermostat/aws.py
django_thermostat/domotic.py
django_thermostat/models.py
django_thermostat/rules.py
django_thermostat/settings.py
django_thermostat/temperature.py
django_thermostat/temperature.py.off
django_thermostat/test_pypelib.py
django_thermostat/tests.py
django_thermostat/urls.py
django_thermostat/utils.py
django_thermostat/views.py
django_thermostat.egg-info/PKG-INFO
django_thermostat.egg-info/SOURCES.txt
django_thermostat.egg-info/dependency_links.txt
django_thermostat.egg-info/requires.txt
django_thermostat.egg-info/top_level.txt
django_thermostat/management/__init__.py
django_thermostat/management/commands/__init__.py
django_thermostat/management/commands/evaluate_non_thermostat.py
django_thermostat/management/commands/evaluate_therm_daemon.py
django_thermostat/management/commands/evaluate_thermostat.py
django_thermostat/management/commands/init_thermometers.py
django_thermostat/management/commands/parse_flame_stats.py
django_thermostat/mappings/__init__.py
django_thermostat/mappings/dimmers.py
django_thermostat/mappings/timings.py
django_thermostat/mappings/utils.py
django_thermostat/mappings/weather.py
django_thermostat/pypelib/Condition.py
django_thermostat/pypelib/Rule.py
django_thermostat/pypelib/RuleTable.py
django_thermostat/pypelib/__init__.py
django_thermostat/pypelib/parsing/ParseEngine.py
django_thermostat/pypelib/parsing/__init__.py
django_thermostat/pypelib/parsing/drivers/RegexParser.py
django_thermostat/pypelib/parsing/drivers/__init__.py
django_thermostat/pypelib/persistence/PersistenceEngine.py
django_thermostat/pypelib/persistence/__init__.py
django_thermostat/pypelib/persistence/backends/__init__.py
django_thermostat/pypelib/persistence/backends/django/Django.py
django_thermostat/pypelib/persistence/backends/django/RuleModel.py
django_thermostat/pypelib/persistence/backends/django/RuleTableModel.py
django_thermostat/pypelib/persistence/backends/django/__init__.py
django_thermostat/pypelib/persistence/backends/rawfile/RAWFile.py
django_thermostat/pypelib/persistence/backends/rawfile/__init__.py
